README.md
setup.py
pr_task.egg-info/PKG-INFO
pr_task.egg-info/SOURCES.txt
pr_task.egg-info/dependency_links.txt
pr_task.egg-info/requires.txt
pr_task.egg-info/top_level.txt
prtask/__init__.py
prtask/config/__init__.py
prtask/config/main.py
prtask/core/__init__.py
prtask/core/aioRedis.py
prtask/log/__init__.py
prtask/log/log.py